europa_1400_tools/__init__.py
europa_1400_tools/__main__.py
europa_1400_tools/commands.py
europa_1400_tools/const.py
europa_1400_tools/construct/ageb.py
europa_1400_tools/construct/aobj.py
europa_1400_tools/construct/baf.py
europa_1400_tools/construct/base_construct.py
europa_1400_tools/construct/bgf.py
europa_1400_tools/construct/common.py
europa_1400_tools/construct/ed3.py
europa_1400_tools/construct/gfx.py
europa_1400_tools/construct/ogr.py
europa_1400_tools/construct/sbf.py
europa_1400_tools/converter/__init__.py
europa_1400_tools/converter/ageb_converter.py
europa_1400_tools/converter/aobj_converter.py
europa_1400_tools/converter/base_converter.py
europa_1400_tools/converter/bgf_converter.py
europa_1400_tools/converter/bgf_gltf_converter.py
europa_1400_tools/converter/bgf_wavefront_converter.py
europa_1400_tools/converter/commands.py
europa_1400_tools/converter/ed3_converter.py
europa_1400_tools/converter/gfx_converter.py
europa_1400_tools/converter/ogr_converter.py
europa_1400_tools/converter/sbf_converter.py
europa_1400_tools/decoder/__init__.py
europa_1400_tools/decoder/commands.py
europa_1400_tools/extractor/__init__.py
europa_1400_tools/extractor/commands.py
europa_1400_tools/helpers.py
europa_1400_tools/mapper/animations_mapper.py
europa_1400_tools/mapper/commands.py
europa_1400_tools/models.py
europa_1400_tools-1.0.7.dist-info/LICENSE
europa_1400_tools-1.0.7.dist-info/METADATA
europa_1400_tools-1.0.7.dist-info/WHEEL
europa_1400_tools-1.0.7.dist-info/entry_points.txt
europa_1400_tools-1.0.7.dist-info/RECORD
